{
  "variants": {
    "distance=1,persistent=false": {
      "model": "minecraft:map/block/screw_horizon"
    },
    "distance=1,persistent=true": {
      "model": "minecraft:map/block/screw_horizon",
	  "y": 90
    },
    "distance=2,persistent=false": {
      "model": "minecraft:map/block/screw_horizon",
	  "y": 180
    },
    "distance=2,persistent=true": {
      "model": "minecraft:map/block/screw_horizon",
	  "y": 270
    },
	"distance=3,persistent=false": {
      "model": "minecraft:map/block/screw_orange"
    },
	"distance=3,persistent=true": {
      "model": "minecraft:map/block/screw_orange_down"
    },
	"distance=4,persistent=false": {
      "model": "minecraft:map/block/screw_pink"
    },
	"distance=4,persistent=true": {
      "model": "minecraft:map/block/screw_pink_down"
    },
	"distance=5,persistent=false": {
      "model": "minecraft:map/block/screw_aqua"
    },
	"distance=5,persistent=true": {
      "model": "minecraft:map/block/screw_aqua_down"
    }
  }
}